LICENCE.TXT
MANIFEST.in
README.txt
setup.py
blast_score_ratio/__init__.py
blast_score_ratio/bsr.py
blast_score_ratio/demo.py
blast_score_ratio.egg-info/PKG-INFO
blast_score_ratio.egg-info/SOURCES.txt
blast_score_ratio.egg-info/dependency_links.txt
blast_score_ratio.egg-info/requires.txt
blast_score_ratio.egg-info/top_level.txt
blast_score_ratio/Examples/example_A.faa
blast_score_ratio/Examples/example_B.faa
blast_score_ratio/Examples/example_C.faa
blast_score_ratio/Examples/example_D.faa
blast_score_ratio/Examples/hgt_seqs.faa