Metadata-Version: 1.1
Name: blast-score-ratio
Version: 1.0.6
Summary: Get BLAST Score Ratios (BSR; as described in Rasko et al (2006) doi:10.1186/1471-2105-6-2)
Home-page: UNKNOWN
Author: John C. Thomas
Author-email: jaytee00@gmail.com
License:  GNU GPLv3
Keywords: comparative genomics biopython bioinformatics protein blast BSR
Platform: UNKNOWN
Classifier: Programming Language :: Python :: 3
Classifier: Development Status :: 4 - beta
